wolfhece_tools/PyPalette.py
wolfhece_tools/PyVertex.py
wolfhece_tools/PyVertexvectors.py
wolfhece_tools/__init__.py
wolfhece_tools/wolf_array.py
wolfhece_tools-0.0.6.dist-info/METADATA
wolfhece_tools-0.0.6.dist-info/WHEEL
wolfhece_tools-0.0.6.dist-info/top_level.txt
wolfhece_tools-0.0.6.dist-info/RECORD
